{"audio_filepath": "../Dataset/Audio/Dev\\zyffh.wav", "offset": 0.04, "duration": 1.0, "label": "UNK", "uniq_id": null}
{"audio_filepath": "../Dataset/Audio/Dev\\zyffh.wav", "offset": 0.54, "duration": 1.0, "label": "UNK", "uniq_id": null}
{"audio_filepath": "../Dataset/Audio/Dev\\zyffh.wav", "offset": 1.04, "duration": 1.0, "label": "UNK", "uniq_id": null}
{"audio_filepath": "../Dataset/Audio/Dev\\zyffh.wav", "offset": 1.54, "duration": 1.0, "label": "UNK", "uniq_id": null}
{"audio_filepath": "../Dataset/Audio/Dev\\zyffh.wav", "offset": 2.04, "duration": 1.0, "label": "UNK", "uniq_id": null}
{"audio_filepath": "../Dataset/Audio/Dev\\zyffh.wav", "offset": 2.54, "duration": 1.0, "label": "UNK", "uniq_id": null}
{"audio_filepath": "../Dataset/Audio/Dev\\zyffh.wav", "offset": 3.04, "duration": 1.0, "label": "UNK", "uniq_id": null}
{"audio_filepath": "../Dataset/Audio/Dev\\zyffh.wav", "offset": 3.54, "duration": 1.0, "label": "UNK", "uniq_id": null}
{"audio_filepath": "../Dataset/Audio/Dev\\zyffh.wav", "offset": 4.04, "duration": 1.0, "label": "UNK", "uniq_id": null}
{"audio_filepath": "../Dataset/Audio/Dev\\zyffh.wav", "offset": 4.54, "duration": 1.0, "label": "UNK", "uniq_id": null}
{"audio_filepath": "../Dataset/Audio/Dev\\zyffh.wav", "offset": 5.04, "duration": 1.0, "label": "UNK", "uniq_id": null}
{"audio_filepath": "../Dataset/Audio/Dev\\zyffh.wav", "offset": 5.54, "duration": 1.0, "label": "UNK", "uniq_id": null}
{"audio_filepath": "../Dataset/Audio/Dev\\zyffh.wav", "offset": 6.04, "duration": 1.0, "label": "UNK", "uniq_id": null}
{"audio_filepath": "../Dataset/Audio/Dev\\zyffh.wav", "offset": 6.54, "duration": 1.0, "label": "UNK", "uniq_id": null}
{"audio_filepath": "../Dataset/Audio/Dev\\zyffh.wav", "offset": 7.04, "duration": 0.9999999999999991, "label": "UNK", "uniq_id": null}
{"audio_filepath": "../Dataset/Audio/Dev\\zyffh.wav", "offset": 7.54, "duration": 0.9999999999999991, "label": "UNK", "uniq_id": null}
{"audio_filepath": "../Dataset/Audio/Dev\\zyffh.wav", "offset": 8.04, "duration": 1.0, "label": "UNK", "uniq_id": null}
{"audio_filepath": "../Dataset/Audio/Dev\\zyffh.wav", "offset": 8.54, "duration": 1.0, "label": "UNK", "uniq_id": null}
{"audio_filepath": "../Dataset/Audio/Dev\\zyffh.wav", "offset": 9.04, "duration": 0.5600000000000005, "label": "UNK", "uniq_id": null}
{"audio_filepath": "../Dataset/Audio/Dev\\zyffh.wav", "offset": 9.92, "duration": 0.6400000000000006, "label": "UNK", "uniq_id": null}
{"audio_filepath": "../Dataset/Audio/Dev\\zyffh.wav", "offset": 11.0, "duration": 1.0, "label": "UNK", "uniq_id": null}
{"audio_filepath": "../Dataset/Audio/Dev\\zyffh.wav", "offset": 11.5, "duration": 1.0, "label": "UNK", "uniq_id": null}
{"audio_filepath": "../Dataset/Audio/Dev\\zyffh.wav", "offset": 12.0, "duration": 1.0, "label": "UNK", "uniq_id": null}
{"audio_filepath": "../Dataset/Audio/Dev\\zyffh.wav", "offset": 12.5, "duration": 1.0, "label": "UNK", "uniq_id": null}
{"audio_filepath": "../Dataset/Audio/Dev\\zyffh.wav", "offset": 13.0, "duration": 1.0, "label": "UNK", "uniq_id": null}
{"audio_filepath": "../Dataset/Audio/Dev\\zyffh.wav", "offset": 13.5, "duration": 1.0, "label": "UNK", "uniq_id": null}
{"audio_filepath": "../Dataset/Audio/Dev\\zyffh.wav", "offset": 14.0, "duration": 1.0, "label": "UNK", "uniq_id": null}
{"audio_filepath": "../Dataset/Audio/Dev\\zyffh.wav", "offset": 14.5, "duration": 1.0, "label": "UNK", "uniq_id": null}
{"audio_filepath": "../Dataset/Audio/Dev\\zyffh.wav", "offset": 15.0, "duration": 1.0, "label": "UNK", "uniq_id": null}
{"audio_filepath": "../Dataset/Audio/Dev\\zyffh.wav", "offset": 15.5, "duration": 0.740000000000002, "label": "UNK", "uniq_id": null}
{"audio_filepath": "../Dataset/Audio/Dev\\zyffh.wav", "offset": 16.48, "duration": 1.0, "label": "UNK", "uniq_id": null}
{"audio_filepath": "../Dataset/Audio/Dev\\zyffh.wav", "offset": 16.98, "duration": 1.0, "label": "UNK", "uniq_id": null}
{"audio_filepath": "../Dataset/Audio/Dev\\zyffh.wav", "offset": 17.48, "duration": 1.0, "label": "UNK", "uniq_id": null}
{"audio_filepath": "../Dataset/Audio/Dev\\zyffh.wav", "offset": 17.98, "duration": 1.0, "label": "UNK", "uniq_id": null}
{"audio_filepath": "../Dataset/Audio/Dev\\zyffh.wav", "offset": 18.48, "duration": 1.0, "label": "UNK", "uniq_id": null}
{"audio_filepath": "../Dataset/Audio/Dev\\zyffh.wav", "offset": 18.98, "duration": 1.0, "label": "UNK", "uniq_id": null}
{"audio_filepath": "../Dataset/Audio/Dev\\zyffh.wav", "offset": 19.48, "duration": 1.0, "label": "UNK", "uniq_id": null}
{"audio_filepath": "../Dataset/Audio/Dev\\zyffh.wav", "offset": 19.98, "duration": 0.7399999999999984, "label": "UNK", "uniq_id": null}
{"audio_filepath": "../Dataset/Audio/Dev\\zyffh.wav", "offset": 21.2, "duration": 1.0, "label": "UNK", "uniq_id": null}
{"audio_filepath": "../Dataset/Audio/Dev\\zyffh.wav", "offset": 21.7, "duration": 0.8200000000000003, "label": "UNK", "uniq_id": null}
{"audio_filepath": "../Dataset/Audio/Dev\\zyffh.wav", "offset": 23.12, "duration": 1.0, "label": "UNK", "uniq_id": null}
{"audio_filepath": "../Dataset/Audio/Dev\\zyffh.wav", "offset": 23.62, "duration": 1.0, "label": "UNK", "uniq_id": null}
{"audio_filepath": "../Dataset/Audio/Dev\\zyffh.wav", "offset": 24.12, "duration": 1.0, "label": "UNK", "uniq_id": null}
{"audio_filepath": "../Dataset/Audio/Dev\\zyffh.wav", "offset": 24.62, "duration": 1.0, "label": "UNK", "uniq_id": null}
{"audio_filepath": "../Dataset/Audio/Dev\\zyffh.wav", "offset": 25.12, "duration": 1.0, "label": "UNK", "uniq_id": null}
{"audio_filepath": "../Dataset/Audio/Dev\\zyffh.wav", "offset": 25.62, "duration": 1.0, "label": "UNK", "uniq_id": null}
{"audio_filepath": "../Dataset/Audio/Dev\\zyffh.wav", "offset": 26.12, "duration": 1.0, "label": "UNK", "uniq_id": null}
{"audio_filepath": "../Dataset/Audio/Dev\\zyffh.wav", "offset": 26.62, "duration": 1.0, "label": "UNK", "uniq_id": null}
{"audio_filepath": "../Dataset/Audio/Dev\\zyffh.wav", "offset": 27.12, "duration": 1.0, "label": "UNK", "uniq_id": null}
{"audio_filepath": "../Dataset/Audio/Dev\\zyffh.wav", "offset": 27.62, "duration": 1.0, "label": "UNK", "uniq_id": null}
{"audio_filepath": "../Dataset/Audio/Dev\\zyffh.wav", "offset": 28.12, "duration": 1.0, "label": "UNK", "uniq_id": null}
{"audio_filepath": "../Dataset/Audio/Dev\\zyffh.wav", "offset": 28.62, "duration": 1.0, "label": "UNK", "uniq_id": null}
{"audio_filepath": "../Dataset/Audio/Dev\\zyffh.wav", "offset": 29.12, "duration": 1.0, "label": "UNK", "uniq_id": null}
{"audio_filepath": "../Dataset/Audio/Dev\\zyffh.wav", "offset": 29.62, "duration": 1.0, "label": "UNK", "uniq_id": null}
{"audio_filepath": "../Dataset/Audio/Dev\\zyffh.wav", "offset": 30.12, "duration": 1.0, "label": "UNK", "uniq_id": null}
{"audio_filepath": "../Dataset/Audio/Dev\\zyffh.wav", "offset": 30.62, "duration": 1.0, "label": "UNK", "uniq_id": null}
{"audio_filepath": "../Dataset/Audio/Dev\\zyffh.wav", "offset": 31.12, "duration": 1.0000000000000036, "label": "UNK", "uniq_id": null}
{"audio_filepath": "../Dataset/Audio/Dev\\zyffh.wav", "offset": 31.62, "duration": 1.0000000000000036, "label": "UNK", "uniq_id": null}
{"audio_filepath": "../Dataset/Audio/Dev\\zyffh.wav", "offset": 32.120000000000005, "duration": 1.0, "label": "UNK", "uniq_id": null}
{"audio_filepath": "../Dataset/Audio/Dev\\zyffh.wav", "offset": 32.620000000000005, "duration": 1.0, "label": "UNK", "uniq_id": null}
{"audio_filepath": "../Dataset/Audio/Dev\\zyffh.wav", "offset": 33.120000000000005, "duration": 1.0, "label": "UNK", "uniq_id": null}
{"audio_filepath": "../Dataset/Audio/Dev\\zyffh.wav", "offset": 33.620000000000005, "duration": 1.0, "label": "UNK", "uniq_id": null}
{"audio_filepath": "../Dataset/Audio/Dev\\zyffh.wav", "offset": 34.120000000000005, "duration": 1.0, "label": "UNK", "uniq_id": null}
{"audio_filepath": "../Dataset/Audio/Dev\\zyffh.wav", "offset": 34.620000000000005, "duration": 1.0, "label": "UNK", "uniq_id": null}
{"audio_filepath": "../Dataset/Audio/Dev\\zyffh.wav", "offset": 35.120000000000005, "duration": 1.0, "label": "UNK", "uniq_id": null}
{"audio_filepath": "../Dataset/Audio/Dev\\zyffh.wav", "offset": 35.620000000000005, "duration": 1.0, "label": "UNK", "uniq_id": null}
{"audio_filepath": "../Dataset/Audio/Dev\\zyffh.wav", "offset": 36.120000000000005, "duration": 1.0, "label": "UNK", "uniq_id": null}
{"audio_filepath": "../Dataset/Audio/Dev\\zyffh.wav", "offset": 36.620000000000005, "duration": 1.0, "label": "UNK", "uniq_id": null}
{"audio_filepath": "../Dataset/Audio/Dev\\zyffh.wav", "offset": 37.120000000000005, "duration": 1.0, "label": "UNK", "uniq_id": null}
{"audio_filepath": "../Dataset/Audio/Dev\\zyffh.wav", "offset": 37.620000000000005, "duration": 1.0, "label": "UNK", "uniq_id": null}
{"audio_filepath": "../Dataset/Audio/Dev\\zyffh.wav", "offset": 38.120000000000005, "duration": 1.0, "label": "UNK", "uniq_id": null}
{"audio_filepath": "../Dataset/Audio/Dev\\zyffh.wav", "offset": 38.620000000000005, "duration": 1.0, "label": "UNK", "uniq_id": null}
{"audio_filepath": "../Dataset/Audio/Dev\\zyffh.wav", "offset": 39.120000000000005, "duration": 1.0, "label": "UNK", "uniq_id": null}
{"audio_filepath": "../Dataset/Audio/Dev\\zyffh.wav", "offset": 39.620000000000005, "duration": 1.0, "label": "UNK", "uniq_id": null}
{"audio_filepath": "../Dataset/Audio/Dev\\zyffh.wav", "offset": 40.120000000000005, "duration": 1.0, "label": "UNK", "uniq_id": null}
{"audio_filepath": "../Dataset/Audio/Dev\\zyffh.wav", "offset": 40.620000000000005, "duration": 1.0, "label": "UNK", "uniq_id": null}
{"audio_filepath": "../Dataset/Audio/Dev\\zyffh.wav", "offset": 41.120000000000005, "duration": 1.0, "label": "UNK", "uniq_id": null}
{"audio_filepath": "../Dataset/Audio/Dev\\zyffh.wav", "offset": 41.620000000000005, "duration": 1.0, "label": "UNK", "uniq_id": null}
{"audio_filepath": "../Dataset/Audio/Dev\\zyffh.wav", "offset": 42.120000000000005, "duration": 1.0, "label": "UNK", "uniq_id": null}
{"audio_filepath": "../Dataset/Audio/Dev\\zyffh.wav", "offset": 42.620000000000005, "duration": 1.0, "label": "UNK", "uniq_id": null}
{"audio_filepath": "../Dataset/Audio/Dev\\zyffh.wav", "offset": 43.120000000000005, "duration": 1.0, "label": "UNK", "uniq_id": null}
{"audio_filepath": "../Dataset/Audio/Dev\\zyffh.wav", "offset": 43.620000000000005, "duration": 1.0, "label": "UNK", "uniq_id": null}
{"audio_filepath": "../Dataset/Audio/Dev\\zyffh.wav", "offset": 44.120000000000005, "duration": 1.0, "label": "UNK", "uniq_id": null}
{"audio_filepath": "../Dataset/Audio/Dev\\zyffh.wav", "offset": 44.620000000000005, "duration": 1.0, "label": "UNK", "uniq_id": null}
{"audio_filepath": "../Dataset/Audio/Dev\\zyffh.wav", "offset": 45.120000000000005, "duration": 1.0, "label": "UNK", "uniq_id": null}
{"audio_filepath": "../Dataset/Audio/Dev\\zyffh.wav", "offset": 45.620000000000005, "duration": 1.0, "label": "UNK", "uniq_id": null}
{"audio_filepath": "../Dataset/Audio/Dev\\zyffh.wav", "offset": 46.120000000000005, "duration": 1.0, "label": "UNK", "uniq_id": null}
{"audio_filepath": "../Dataset/Audio/Dev\\zyffh.wav", "offset": 46.620000000000005, "duration": 1.0, "label": "UNK", "uniq_id": null}
{"audio_filepath": "../Dataset/Audio/Dev\\zyffh.wav", "offset": 47.120000000000005, "duration": 1.0, "label": "UNK", "uniq_id": null}
{"audio_filepath": "../Dataset/Audio/Dev\\zyffh.wav", "offset": 47.620000000000005, "duration": 1.0, "label": "UNK", "uniq_id": null}
{"audio_filepath": "../Dataset/Audio/Dev\\zyffh.wav", "offset": 48.120000000000005, "duration": 1.0, "label": "UNK", "uniq_id": null}
{"audio_filepath": "../Dataset/Audio/Dev\\zyffh.wav", "offset": 48.620000000000005, "duration": 1.0, "label": "UNK", "uniq_id": null}
{"audio_filepath": "../Dataset/Audio/Dev\\zyffh.wav", "offset": 49.120000000000005, "duration": 1.0, "label": "UNK", "uniq_id": null}
{"audio_filepath": "../Dataset/Audio/Dev\\zyffh.wav", "offset": 49.620000000000005, "duration": 1.0, "label": "UNK", "uniq_id": null}
{"audio_filepath": "../Dataset/Audio/Dev\\zyffh.wav", "offset": 50.120000000000005, "duration": 1.0, "label": "UNK", "uniq_id": null}
{"audio_filepath": "../Dataset/Audio/Dev\\zyffh.wav", "offset": 50.620000000000005, "duration": 1.0, "label": "UNK", "uniq_id": null}
{"audio_filepath": "../Dataset/Audio/Dev\\zyffh.wav", "offset": 51.120000000000005, "duration": 1.0, "label": "UNK", "uniq_id": null}
{"audio_filepath": "../Dataset/Audio/Dev\\zyffh.wav", "offset": 51.620000000000005, "duration": 1.0, "label": "UNK", "uniq_id": null}
{"audio_filepath": "../Dataset/Audio/Dev\\zyffh.wav", "offset": 52.120000000000005, "duration": 1.0, "label": "UNK", "uniq_id": null}
{"audio_filepath": "../Dataset/Audio/Dev\\zyffh.wav", "offset": 52.620000000000005, "duration": 1.0, "label": "UNK", "uniq_id": null}
{"audio_filepath": "../Dataset/Audio/Dev\\zyffh.wav", "offset": 53.120000000000005, "duration": 1.0, "label": "UNK", "uniq_id": null}
{"audio_filepath": "../Dataset/Audio/Dev\\zyffh.wav", "offset": 53.620000000000005, "duration": 1.0, "label": "UNK", "uniq_id": null}
{"audio_filepath": "../Dataset/Audio/Dev\\zyffh.wav", "offset": 54.120000000000005, "duration": 1.0, "label": "UNK", "uniq_id": null}
{"audio_filepath": "../Dataset/Audio/Dev\\zyffh.wav", "offset": 54.620000000000005, "duration": 1.0, "label": "UNK", "uniq_id": null}
{"audio_filepath": "../Dataset/Audio/Dev\\zyffh.wav", "offset": 55.120000000000005, "duration": 1.0, "label": "UNK", "uniq_id": null}
{"audio_filepath": "../Dataset/Audio/Dev\\zyffh.wav", "offset": 55.620000000000005, "duration": 1.0, "label": "UNK", "uniq_id": null}
{"audio_filepath": "../Dataset/Audio/Dev\\zyffh.wav", "offset": 56.120000000000005, "duration": 1.0, "label": "UNK", "uniq_id": null}
{"audio_filepath": "../Dataset/Audio/Dev\\zyffh.wav", "offset": 56.620000000000005, "duration": 1.0, "label": "UNK", "uniq_id": null}
{"audio_filepath": "../Dataset/Audio/Dev\\zyffh.wav", "offset": 57.120000000000005, "duration": 1.0, "label": "UNK", "uniq_id": null}
{"audio_filepath": "../Dataset/Audio/Dev\\zyffh.wav", "offset": 57.620000000000005, "duration": 1.0, "label": "UNK", "uniq_id": null}
{"audio_filepath": "../Dataset/Audio/Dev\\zyffh.wav", "offset": 58.120000000000005, "duration": 1.0, "label": "UNK", "uniq_id": null}
{"audio_filepath": "../Dataset/Audio/Dev\\zyffh.wav", "offset": 58.620000000000005, "duration": 1.0, "label": "UNK", "uniq_id": null}
{"audio_filepath": "../Dataset/Audio/Dev\\zyffh.wav", "offset": 59.120000000000005, "duration": 1.0, "label": "UNK", "uniq_id": null}
{"audio_filepath": "../Dataset/Audio/Dev\\zyffh.wav", "offset": 59.620000000000005, "duration": 1.0, "label": "UNK", "uniq_id": null}
{"audio_filepath": "../Dataset/Audio/Dev\\zyffh.wav", "offset": 60.120000000000005, "duration": 1.0, "label": "UNK", "uniq_id": null}
{"audio_filepath": "../Dataset/Audio/Dev\\zyffh.wav", "offset": 60.620000000000005, "duration": 1.0, "label": "UNK", "uniq_id": null}
{"audio_filepath": "../Dataset/Audio/Dev\\zyffh.wav", "offset": 61.120000000000005, "duration": 1.0, "label": "UNK", "uniq_id": null}
{"audio_filepath": "../Dataset/Audio/Dev\\zyffh.wav", "offset": 61.620000000000005, "duration": 1.0, "label": "UNK", "uniq_id": null}
{"audio_filepath": "../Dataset/Audio/Dev\\zyffh.wav", "offset": 62.120000000000005, "duration": 1.0, "label": "UNK", "uniq_id": null}
{"audio_filepath": "../Dataset/Audio/Dev\\zyffh.wav", "offset": 62.620000000000005, "duration": 1.0, "label": "UNK", "uniq_id": null}
{"audio_filepath": "../Dataset/Audio/Dev\\zyffh.wav", "offset": 63.120000000000005, "duration": 1.0, "label": "UNK", "uniq_id": null}
{"audio_filepath": "../Dataset/Audio/Dev\\zyffh.wav", "offset": 63.620000000000005, "duration": 1.0, "label": "UNK", "uniq_id": null}
{"audio_filepath": "../Dataset/Audio/Dev\\zyffh.wav", "offset": 64.12, "duration": 1.0, "label": "UNK", "uniq_id": null}
{"audio_filepath": "../Dataset/Audio/Dev\\zyffh.wav", "offset": 64.62, "duration": 1.0, "label": "UNK", "uniq_id": null}
{"audio_filepath": "../Dataset/Audio/Dev\\zyffh.wav", "offset": 65.12, "duration": 1.0, "label": "UNK", "uniq_id": null}
{"audio_filepath": "../Dataset/Audio/Dev\\zyffh.wav", "offset": 65.62, "duration": 1.0, "label": "UNK", "uniq_id": null}
{"audio_filepath": "../Dataset/Audio/Dev\\zyffh.wav", "offset": 66.12, "duration": 1.0, "label": "UNK", "uniq_id": null}
{"audio_filepath": "../Dataset/Audio/Dev\\zyffh.wav", "offset": 66.62, "duration": 1.0, "label": "UNK", "uniq_id": null}
{"audio_filepath": "../Dataset/Audio/Dev\\zyffh.wav", "offset": 67.12, "duration": 1.0, "label": "UNK", "uniq_id": null}
{"audio_filepath": "../Dataset/Audio/Dev\\zyffh.wav", "offset": 67.62, "duration": 1.0, "label": "UNK", "uniq_id": null}
{"audio_filepath": "../Dataset/Audio/Dev\\zyffh.wav", "offset": 68.12, "duration": 1.0, "label": "UNK", "uniq_id": null}
{"audio_filepath": "../Dataset/Audio/Dev\\zyffh.wav", "offset": 68.62, "duration": 1.0, "label": "UNK", "uniq_id": null}
{"audio_filepath": "../Dataset/Audio/Dev\\zyffh.wav", "offset": 69.12, "duration": 1.0, "label": "UNK", "uniq_id": null}
{"audio_filepath": "../Dataset/Audio/Dev\\zyffh.wav", "offset": 69.62, "duration": 1.0, "label": "UNK", "uniq_id": null}
{"audio_filepath": "../Dataset/Audio/Dev\\zyffh.wav", "offset": 70.12, "duration": 1.0, "label": "UNK", "uniq_id": null}
{"audio_filepath": "../Dataset/Audio/Dev\\zyffh.wav", "offset": 70.62, "duration": 1.0, "label": "UNK", "uniq_id": null}
{"audio_filepath": "../Dataset/Audio/Dev\\zyffh.wav", "offset": 71.12, "duration": 1.0, "label": "UNK", "uniq_id": null}
{"audio_filepath": "../Dataset/Audio/Dev\\zyffh.wav", "offset": 71.62, "duration": 1.0, "label": "UNK", "uniq_id": null}
{"audio_filepath": "../Dataset/Audio/Dev\\zyffh.wav", "offset": 72.12, "duration": 1.0, "label": "UNK", "uniq_id": null}
{"audio_filepath": "../Dataset/Audio/Dev\\zyffh.wav", "offset": 72.62, "duration": 1.0, "label": "UNK", "uniq_id": null}
{"audio_filepath": "../Dataset/Audio/Dev\\zyffh.wav", "offset": 73.12, "duration": 1.0, "label": "UNK", "uniq_id": null}
{"audio_filepath": "../Dataset/Audio/Dev\\zyffh.wav", "offset": 73.62, "duration": 0.9399999999999977, "label": "UNK", "uniq_id": null}
{"audio_filepath": "../Dataset/Audio/Dev\\zyffh.wav", "offset": 75.2, "duration": 1.0, "label": "UNK", "uniq_id": null}
{"audio_filepath": "../Dataset/Audio/Dev\\zyffh.wav", "offset": 75.7, "duration": 0.8199999999999932, "label": "UNK", "uniq_id": null}
{"audio_filepath": "../Dataset/Audio/Dev\\zyffh.wav", "offset": 76.76, "duration": 1.0, "label": "UNK", "uniq_id": null}
{"audio_filepath": "../Dataset/Audio/Dev\\zyffh.wav", "offset": 77.26, "duration": 1.0, "label": "UNK", "uniq_id": null}
{"audio_filepath": "../Dataset/Audio/Dev\\zyffh.wav", "offset": 77.76, "duration": 1.0, "label": "UNK", "uniq_id": null}
{"audio_filepath": "../Dataset/Audio/Dev\\zyffh.wav", "offset": 78.26, "duration": 1.0, "label": "UNK", "uniq_id": null}
{"audio_filepath": "../Dataset/Audio/Dev\\zyffh.wav", "offset": 78.76, "duration": 1.0, "label": "UNK", "uniq_id": null}
{"audio_filepath": "../Dataset/Audio/Dev\\zyffh.wav", "offset": 79.26, "duration": 1.0, "label": "UNK", "uniq_id": null}
{"audio_filepath": "../Dataset/Audio/Dev\\zyffh.wav", "offset": 79.76, "duration": 1.0, "label": "UNK", "uniq_id": null}
{"audio_filepath": "../Dataset/Audio/Dev\\zyffh.wav", "offset": 80.26, "duration": 1.0, "label": "UNK", "uniq_id": null}
{"audio_filepath": "../Dataset/Audio/Dev\\zyffh.wav", "offset": 80.76, "duration": 1.0, "label": "UNK", "uniq_id": null}
{"audio_filepath": "../Dataset/Audio/Dev\\zyffh.wav", "offset": 81.26, "duration": 1.0, "label": "UNK", "uniq_id": null}
{"audio_filepath": "../Dataset/Audio/Dev\\zyffh.wav", "offset": 81.76, "duration": 1.0, "label": "UNK", "uniq_id": null}
{"audio_filepath": "../Dataset/Audio/Dev\\zyffh.wav", "offset": 82.26, "duration": 1.0, "label": "UNK", "uniq_id": null}
{"audio_filepath": "../Dataset/Audio/Dev\\zyffh.wav", "offset": 82.76, "duration": 1.0, "label": "UNK", "uniq_id": null}
{"audio_filepath": "../Dataset/Audio/Dev\\zyffh.wav", "offset": 83.26, "duration": 1.0, "label": "UNK", "uniq_id": null}
{"audio_filepath": "../Dataset/Audio/Dev\\zyffh.wav", "offset": 83.76, "duration": 1.0, "label": "UNK", "uniq_id": null}
{"audio_filepath": "../Dataset/Audio/Dev\\zyffh.wav", "offset": 84.26, "duration": 1.0, "label": "UNK", "uniq_id": null}
{"audio_filepath": "../Dataset/Audio/Dev\\zyffh.wav", "offset": 84.76, "duration": 1.0, "label": "UNK", "uniq_id": null}
{"audio_filepath": "../Dataset/Audio/Dev\\zyffh.wav", "offset": 85.26, "duration": 1.0, "label": "UNK", "uniq_id": null}
{"audio_filepath": "../Dataset/Audio/Dev\\zyffh.wav", "offset": 85.76, "duration": 1.0, "label": "UNK", "uniq_id": null}
{"audio_filepath": "../Dataset/Audio/Dev\\zyffh.wav", "offset": 86.26, "duration": 1.0, "label": "UNK", "uniq_id": null}
{"audio_filepath": "../Dataset/Audio/Dev\\zyffh.wav", "offset": 86.76, "duration": 1.0, "label": "UNK", "uniq_id": null}
{"audio_filepath": "../Dataset/Audio/Dev\\zyffh.wav", "offset": 87.26, "duration": 1.0, "label": "UNK", "uniq_id": null}
{"audio_filepath": "../Dataset/Audio/Dev\\zyffh.wav", "offset": 87.76, "duration": 1.0, "label": "UNK", "uniq_id": null}
{"audio_filepath": "../Dataset/Audio/Dev\\zyffh.wav", "offset": 88.26, "duration": 1.0, "label": "UNK", "uniq_id": null}
{"audio_filepath": "../Dataset/Audio/Dev\\zyffh.wav", "offset": 88.76, "duration": 1.0, "label": "UNK", "uniq_id": null}
{"audio_filepath": "../Dataset/Audio/Dev\\zyffh.wav", "offset": 89.26, "duration": 1.0, "label": "UNK", "uniq_id": null}
{"audio_filepath": "../Dataset/Audio/Dev\\zyffh.wav", "offset": 89.76, "duration": 1.0, "label": "UNK", "uniq_id": null}
{"audio_filepath": "../Dataset/Audio/Dev\\zyffh.wav", "offset": 90.26, "duration": 1.0, "label": "UNK", "uniq_id": null}
{"audio_filepath": "../Dataset/Audio/Dev\\zyffh.wav", "offset": 90.76, "duration": 1.0, "label": "UNK", "uniq_id": null}
{"audio_filepath": "../Dataset/Audio/Dev\\zyffh.wav", "offset": 91.26, "duration": 1.0, "label": "UNK", "uniq_id": null}
{"audio_filepath": "../Dataset/Audio/Dev\\zyffh.wav", "offset": 91.76, "duration": 1.0, "label": "UNK", "uniq_id": null}
{"audio_filepath": "../Dataset/Audio/Dev\\zyffh.wav", "offset": 92.26, "duration": 1.0, "label": "UNK", "uniq_id": null}
{"audio_filepath": "../Dataset/Audio/Dev\\zyffh.wav", "offset": 92.76, "duration": 1.0, "label": "UNK", "uniq_id": null}
{"audio_filepath": "../Dataset/Audio/Dev\\zyffh.wav", "offset": 93.26, "duration": 1.0, "label": "UNK", "uniq_id": null}
{"audio_filepath": "../Dataset/Audio/Dev\\zyffh.wav", "offset": 93.76, "duration": 1.0, "label": "UNK", "uniq_id": null}
{"audio_filepath": "../Dataset/Audio/Dev\\zyffh.wav", "offset": 94.26, "duration": 1.0, "label": "UNK", "uniq_id": null}
{"audio_filepath": "../Dataset/Audio/Dev\\zyffh.wav", "offset": 94.76, "duration": 1.0, "label": "UNK", "uniq_id": null}
{"audio_filepath": "../Dataset/Audio/Dev\\zyffh.wav", "offset": 95.26, "duration": 1.0, "label": "UNK", "uniq_id": null}
{"audio_filepath": "../Dataset/Audio/Dev\\zyffh.wav", "offset": 95.76, "duration": 1.0, "label": "UNK", "uniq_id": null}
{"audio_filepath": "../Dataset/Audio/Dev\\zyffh.wav", "offset": 96.26, "duration": 1.0, "label": "UNK", "uniq_id": null}
{"audio_filepath": "../Dataset/Audio/Dev\\zyffh.wav", "offset": 96.76, "duration": 1.0, "label": "UNK", "uniq_id": null}
{"audio_filepath": "../Dataset/Audio/Dev\\zyffh.wav", "offset": 97.26, "duration": 1.0, "label": "UNK", "uniq_id": null}
{"audio_filepath": "../Dataset/Audio/Dev\\zyffh.wav", "offset": 97.76, "duration": 1.0, "label": "UNK", "uniq_id": null}
{"audio_filepath": "../Dataset/Audio/Dev\\zyffh.wav", "offset": 98.26, "duration": 1.0, "label": "UNK", "uniq_id": null}
{"audio_filepath": "../Dataset/Audio/Dev\\zyffh.wav", "offset": 98.76, "duration": 1.0, "label": "UNK", "uniq_id": null}
{"audio_filepath": "../Dataset/Audio/Dev\\zyffh.wav", "offset": 99.26, "duration": 1.0, "label": "UNK", "uniq_id": null}
{"audio_filepath": "../Dataset/Audio/Dev\\zyffh.wav", "offset": 99.76, "duration": 1.0, "label": "UNK", "uniq_id": null}
{"audio_filepath": "../Dataset/Audio/Dev\\zyffh.wav", "offset": 100.26, "duration": 1.0, "label": "UNK", "uniq_id": null}
{"audio_filepath": "../Dataset/Audio/Dev\\zyffh.wav", "offset": 100.76, "duration": 1.0, "label": "UNK", "uniq_id": null}
{"audio_filepath": "../Dataset/Audio/Dev\\zyffh.wav", "offset": 101.26, "duration": 1.0, "label": "UNK", "uniq_id": null}
{"audio_filepath": "../Dataset/Audio/Dev\\zyffh.wav", "offset": 101.76, "duration": 1.0, "label": "UNK", "uniq_id": null}
{"audio_filepath": "../Dataset/Audio/Dev\\zyffh.wav", "offset": 102.26, "duration": 1.0, "label": "UNK", "uniq_id": null}
{"audio_filepath": "../Dataset/Audio/Dev\\zyffh.wav", "offset": 102.76, "duration": 1.0, "label": "UNK", "uniq_id": null}
{"audio_filepath": "../Dataset/Audio/Dev\\zyffh.wav", "offset": 103.26, "duration": 1.0, "label": "UNK", "uniq_id": null}
{"audio_filepath": "../Dataset/Audio/Dev\\zyffh.wav", "offset": 103.76, "duration": 1.0, "label": "UNK", "uniq_id": null}
{"audio_filepath": "../Dataset/Audio/Dev\\zyffh.wav", "offset": 104.26, "duration": 1.0, "label": "UNK", "uniq_id": null}
{"audio_filepath": "../Dataset/Audio/Dev\\zyffh.wav", "offset": 104.76, "duration": 0.6400000000000006, "label": "UNK", "uniq_id": null}
{"audio_filepath": "../Dataset/Audio/Dev\\zyffh.wav", "offset": 105.72, "duration": 1.0, "label": "UNK", "uniq_id": null}
{"audio_filepath": "../Dataset/Audio/Dev\\zyffh.wav", "offset": 106.22, "duration": 1.0, "label": "UNK", "uniq_id": null}
{"audio_filepath": "../Dataset/Audio/Dev\\zyffh.wav", "offset": 106.72, "duration": 1.0, "label": "UNK", "uniq_id": null}
{"audio_filepath": "../Dataset/Audio/Dev\\zyffh.wav", "offset": 107.22, "duration": 1.0, "label": "UNK", "uniq_id": null}
{"audio_filepath": "../Dataset/Audio/Dev\\zyffh.wav", "offset": 107.72, "duration": 1.0, "label": "UNK", "uniq_id": null}
{"audio_filepath": "../Dataset/Audio/Dev\\zyffh.wav", "offset": 108.22, "duration": 1.0, "label": "UNK", "uniq_id": null}
{"audio_filepath": "../Dataset/Audio/Dev\\zyffh.wav", "offset": 108.72, "duration": 1.0, "label": "UNK", "uniq_id": null}
{"audio_filepath": "../Dataset/Audio/Dev\\zyffh.wav", "offset": 109.22, "duration": 1.0, "label": "UNK", "uniq_id": null}
{"audio_filepath": "../Dataset/Audio/Dev\\zyffh.wav", "offset": 109.72, "duration": 1.0, "label": "UNK", "uniq_id": null}
{"audio_filepath": "../Dataset/Audio/Dev\\zyffh.wav", "offset": 110.22, "duration": 1.0, "label": "UNK", "uniq_id": null}
{"audio_filepath": "../Dataset/Audio/Dev\\zyffh.wav", "offset": 110.72, "duration": 1.0, "label": "UNK", "uniq_id": null}
{"audio_filepath": "../Dataset/Audio/Dev\\zyffh.wav", "offset": 111.22, "duration": 1.0, "label": "UNK", "uniq_id": null}
{"audio_filepath": "../Dataset/Audio/Dev\\zyffh.wav", "offset": 111.72, "duration": 1.0, "label": "UNK", "uniq_id": null}
{"audio_filepath": "../Dataset/Audio/Dev\\zyffh.wav", "offset": 112.22, "duration": 1.0, "label": "UNK", "uniq_id": null}
{"audio_filepath": "../Dataset/Audio/Dev\\zyffh.wav", "offset": 112.72, "duration": 1.0, "label": "UNK", "uniq_id": null}
{"audio_filepath": "../Dataset/Audio/Dev\\zyffh.wav", "offset": 113.22, "duration": 1.0, "label": "UNK", "uniq_id": null}
{"audio_filepath": "../Dataset/Audio/Dev\\zyffh.wav", "offset": 113.72, "duration": 1.0, "label": "UNK", "uniq_id": null}
{"audio_filepath": "../Dataset/Audio/Dev\\zyffh.wav", "offset": 114.22, "duration": 1.0, "label": "UNK", "uniq_id": null}
{"audio_filepath": "../Dataset/Audio/Dev\\zyffh.wav", "offset": 114.72, "duration": 1.0, "label": "UNK", "uniq_id": null}
{"audio_filepath": "../Dataset/Audio/Dev\\zyffh.wav", "offset": 115.22, "duration": 1.0, "label": "UNK", "uniq_id": null}
{"audio_filepath": "../Dataset/Audio/Dev\\zyffh.wav", "offset": 115.72, "duration": 1.0, "label": "UNK", "uniq_id": null}
{"audio_filepath": "../Dataset/Audio/Dev\\zyffh.wav", "offset": 116.22, "duration": 1.0, "label": "UNK", "uniq_id": null}
{"audio_filepath": "../Dataset/Audio/Dev\\zyffh.wav", "offset": 116.72, "duration": 1.0, "label": "UNK", "uniq_id": null}
{"audio_filepath": "../Dataset/Audio/Dev\\zyffh.wav", "offset": 117.22, "duration": 1.0, "label": "UNK", "uniq_id": null}
{"audio_filepath": "../Dataset/Audio/Dev\\zyffh.wav", "offset": 117.72, "duration": 1.0, "label": "UNK", "uniq_id": null}
{"audio_filepath": "../Dataset/Audio/Dev\\zyffh.wav", "offset": 118.22, "duration": 1.0, "label": "UNK", "uniq_id": null}
{"audio_filepath": "../Dataset/Audio/Dev\\zyffh.wav", "offset": 118.72, "duration": 1.0, "label": "UNK", "uniq_id": null}
{"audio_filepath": "../Dataset/Audio/Dev\\zyffh.wav", "offset": 119.22, "duration": 1.0, "label": "UNK", "uniq_id": null}
{"audio_filepath": "../Dataset/Audio/Dev\\zyffh.wav", "offset": 119.72, "duration": 1.0, "label": "UNK", "uniq_id": null}
{"audio_filepath": "../Dataset/Audio/Dev\\zyffh.wav", "offset": 120.22, "duration": 1.0, "label": "UNK", "uniq_id": null}
{"audio_filepath": "../Dataset/Audio/Dev\\zyffh.wav", "offset": 120.72, "duration": 1.0, "label": "UNK", "uniq_id": null}
{"audio_filepath": "../Dataset/Audio/Dev\\zyffh.wav", "offset": 121.22, "duration": 1.0, "label": "UNK", "uniq_id": null}
{"audio_filepath": "../Dataset/Audio/Dev\\zyffh.wav", "offset": 121.72, "duration": 1.0, "label": "UNK", "uniq_id": null}
{"audio_filepath": "../Dataset/Audio/Dev\\zyffh.wav", "offset": 122.22, "duration": 1.0, "label": "UNK", "uniq_id": null}
{"audio_filepath": "../Dataset/Audio/Dev\\zyffh.wav", "offset": 122.72, "duration": 1.0, "label": "UNK", "uniq_id": null}
{"audio_filepath": "../Dataset/Audio/Dev\\zyffh.wav", "offset": 123.22, "duration": 1.0, "label": "UNK", "uniq_id": null}
{"audio_filepath": "../Dataset/Audio/Dev\\zyffh.wav", "offset": 123.72, "duration": 1.0, "label": "UNK", "uniq_id": null}
{"audio_filepath": "../Dataset/Audio/Dev\\zyffh.wav", "offset": 124.22, "duration": 1.0, "label": "UNK", "uniq_id": null}
{"audio_filepath": "../Dataset/Audio/Dev\\zyffh.wav", "offset": 124.72, "duration": 1.0, "label": "UNK", "uniq_id": null}
{"audio_filepath": "../Dataset/Audio/Dev\\zyffh.wav", "offset": 125.22, "duration": 1.0, "label": "UNK", "uniq_id": null}
{"audio_filepath": "../Dataset/Audio/Dev\\zyffh.wav", "offset": 125.72, "duration": 1.0, "label": "UNK", "uniq_id": null}
{"audio_filepath": "../Dataset/Audio/Dev\\zyffh.wav", "offset": 126.22, "duration": 1.0, "label": "UNK", "uniq_id": null}
{"audio_filepath": "../Dataset/Audio/Dev\\zyffh.wav", "offset": 126.72, "duration": 1.0, "label": "UNK", "uniq_id": null}
{"audio_filepath": "../Dataset/Audio/Dev\\zyffh.wav", "offset": 127.22, "duration": 1.0, "label": "UNK", "uniq_id": null}
{"audio_filepath": "../Dataset/Audio/Dev\\zyffh.wav", "offset": 127.72, "duration": 1.0, "label": "UNK", "uniq_id": null}
{"audio_filepath": "../Dataset/Audio/Dev\\zyffh.wav", "offset": 128.22, "duration": 1.0, "label": "UNK", "uniq_id": null}
{"audio_filepath": "../Dataset/Audio/Dev\\zyffh.wav", "offset": 128.72, "duration": 1.0, "label": "UNK", "uniq_id": null}
{"audio_filepath": "../Dataset/Audio/Dev\\zyffh.wav", "offset": 129.22, "duration": 1.0, "label": "UNK", "uniq_id": null}
{"audio_filepath": "../Dataset/Audio/Dev\\zyffh.wav", "offset": 129.72, "duration": 1.0, "label": "UNK", "uniq_id": null}
{"audio_filepath": "../Dataset/Audio/Dev\\zyffh.wav", "offset": 130.22, "duration": 0.9799999999999898, "label": "UNK", "uniq_id": null}
{"audio_filepath": "../Dataset/Audio/Dev\\zyffh.wav", "offset": 131.28, "duration": 1.0, "label": "UNK", "uniq_id": null}
{"audio_filepath": "../Dataset/Audio/Dev\\zyffh.wav", "offset": 131.78, "duration": 1.0, "label": "UNK", "uniq_id": null}
{"audio_filepath": "../Dataset/Audio/Dev\\zyffh.wav", "offset": 132.28, "duration": 1.0, "label": "UNK", "uniq_id": null}
{"audio_filepath": "../Dataset/Audio/Dev\\zyffh.wav", "offset": 132.78, "duration": 1.0, "label": "UNK", "uniq_id": null}
{"audio_filepath": "../Dataset/Audio/Dev\\zyffh.wav", "offset": 133.28, "duration": 1.0, "label": "UNK", "uniq_id": null}
{"audio_filepath": "../Dataset/Audio/Dev\\zyffh.wav", "offset": 133.78, "duration": 1.0, "label": "UNK", "uniq_id": null}
{"audio_filepath": "../Dataset/Audio/Dev\\zyffh.wav", "offset": 134.28, "duration": 1.0, "label": "UNK", "uniq_id": null}
{"audio_filepath": "../Dataset/Audio/Dev\\zyffh.wav", "offset": 134.78, "duration": 0.5800000000000125, "label": "UNK", "uniq_id": null}
{"audio_filepath": "../Dataset/Audio/Dev\\zyffh.wav", "offset": 135.39999, "duration": 1.0, "label": "UNK", "uniq_id": null}
{"audio_filepath": "../Dataset/Audio/Dev\\zyffh.wav", "offset": 135.89999, "duration": 1.0, "label": "UNK", "uniq_id": null}
{"audio_filepath": "../Dataset/Audio/Dev\\zyffh.wav", "offset": 136.39999, "duration": 1.0, "label": "UNK", "uniq_id": null}
{"audio_filepath": "../Dataset/Audio/Dev\\zyffh.wav", "offset": 136.89999, "duration": 1.0, "label": "UNK", "uniq_id": null}
{"audio_filepath": "../Dataset/Audio/Dev\\zyffh.wav", "offset": 137.39999, "duration": 1.0, "label": "UNK", "uniq_id": null}
{"audio_filepath": "../Dataset/Audio/Dev\\zyffh.wav", "offset": 137.89999, "duration": 1.0, "label": "UNK", "uniq_id": null}
{"audio_filepath": "../Dataset/Audio/Dev\\zyffh.wav", "offset": 138.39999, "duration": 1.0, "label": "UNK", "uniq_id": null}
{"audio_filepath": "../Dataset/Audio/Dev\\zyffh.wav", "offset": 138.89999, "duration": 1.0, "label": "UNK", "uniq_id": null}
{"audio_filepath": "../Dataset/Audio/Dev\\zyffh.wav", "offset": 139.39999, "duration": 1.0, "label": "UNK", "uniq_id": null}
{"audio_filepath": "../Dataset/Audio/Dev\\zyffh.wav", "offset": 139.89999, "duration": 1.0, "label": "UNK", "uniq_id": null}
{"audio_filepath": "../Dataset/Audio/Dev\\zyffh.wav", "offset": 140.39999, "duration": 1.0, "label": "UNK", "uniq_id": null}
{"audio_filepath": "../Dataset/Audio/Dev\\zyffh.wav", "offset": 140.89999, "duration": 1.0, "label": "UNK", "uniq_id": null}
{"audio_filepath": "../Dataset/Audio/Dev\\zyffh.wav", "offset": 141.39999, "duration": 1.0, "label": "UNK", "uniq_id": null}
{"audio_filepath": "../Dataset/Audio/Dev\\zyffh.wav", "offset": 141.89999, "duration": 1.0, "label": "UNK", "uniq_id": null}
{"audio_filepath": "../Dataset/Audio/Dev\\zyffh.wav", "offset": 142.39999, "duration": 1.0, "label": "UNK", "uniq_id": null}
{"audio_filepath": "../Dataset/Audio/Dev\\zyffh.wav", "offset": 142.89999, "duration": 1.0, "label": "UNK", "uniq_id": null}
{"audio_filepath": "../Dataset/Audio/Dev\\zyffh.wav", "offset": 143.39999, "duration": 1.0, "label": "UNK", "uniq_id": null}
{"audio_filepath": "../Dataset/Audio/Dev\\zyffh.wav", "offset": 143.89999, "duration": 1.0, "label": "UNK", "uniq_id": null}
{"audio_filepath": "../Dataset/Audio/Dev\\zyffh.wav", "offset": 144.39999, "duration": 1.0, "label": "UNK", "uniq_id": null}
{"audio_filepath": "../Dataset/Audio/Dev\\zyffh.wav", "offset": 144.89999, "duration": 1.0, "label": "UNK", "uniq_id": null}
{"audio_filepath": "../Dataset/Audio/Dev\\zyffh.wav", "offset": 145.39999, "duration": 1.0, "label": "UNK", "uniq_id": null}
{"audio_filepath": "../Dataset/Audio/Dev\\zyffh.wav", "offset": 145.89999, "duration": 1.0, "label": "UNK", "uniq_id": null}
{"audio_filepath": "../Dataset/Audio/Dev\\zyffh.wav", "offset": 146.39999, "duration": 1.0, "label": "UNK", "uniq_id": null}
{"audio_filepath": "../Dataset/Audio/Dev\\zyffh.wav", "offset": 146.89999, "duration": 1.0, "label": "UNK", "uniq_id": null}
{"audio_filepath": "../Dataset/Audio/Dev\\zyffh.wav", "offset": 147.39999, "duration": 1.0, "label": "UNK", "uniq_id": null}
{"audio_filepath": "../Dataset/Audio/Dev\\zyffh.wav", "offset": 147.89999, "duration": 1.0, "label": "UNK", "uniq_id": null}
{"audio_filepath": "../Dataset/Audio/Dev\\zyffh.wav", "offset": 148.39999, "duration": 1.0, "label": "UNK", "uniq_id": null}
{"audio_filepath": "../Dataset/Audio/Dev\\zyffh.wav", "offset": 148.89999, "duration": 1.0, "label": "UNK", "uniq_id": null}
{"audio_filepath": "../Dataset/Audio/Dev\\zyffh.wav", "offset": 149.39999, "duration": 1.0, "label": "UNK", "uniq_id": null}
{"audio_filepath": "../Dataset/Audio/Dev\\zyffh.wav", "offset": 149.89999, "duration": 1.0, "label": "UNK", "uniq_id": null}
{"audio_filepath": "../Dataset/Audio/Dev\\zyffh.wav", "offset": 150.39999, "duration": 1.0, "label": "UNK", "uniq_id": null}
{"audio_filepath": "../Dataset/Audio/Dev\\zyffh.wav", "offset": 150.89999, "duration": 1.0, "label": "UNK", "uniq_id": null}
{"audio_filepath": "../Dataset/Audio/Dev\\zyffh.wav", "offset": 151.39999, "duration": 1.0, "label": "UNK", "uniq_id": null}
{"audio_filepath": "../Dataset/Audio/Dev\\zyffh.wav", "offset": 151.89999, "duration": 1.0, "label": "UNK", "uniq_id": null}
{"audio_filepath": "../Dataset/Audio/Dev\\zyffh.wav", "offset": 152.39999, "duration": 1.0, "label": "UNK", "uniq_id": null}
{"audio_filepath": "../Dataset/Audio/Dev\\zyffh.wav", "offset": 152.89999, "duration": 1.0, "label": "UNK", "uniq_id": null}
{"audio_filepath": "../Dataset/Audio/Dev\\zyffh.wav", "offset": 153.39999, "duration": 1.0, "label": "UNK", "uniq_id": null}
{"audio_filepath": "../Dataset/Audio/Dev\\zyffh.wav", "offset": 153.89999, "duration": 1.0, "label": "UNK", "uniq_id": null}
{"audio_filepath": "../Dataset/Audio/Dev\\zyffh.wav", "offset": 154.39999, "duration": 1.0, "label": "UNK", "uniq_id": null}
{"audio_filepath": "../Dataset/Audio/Dev\\zyffh.wav", "offset": 154.89999, "duration": 1.0, "label": "UNK", "uniq_id": null}
{"audio_filepath": "../Dataset/Audio/Dev\\zyffh.wav", "offset": 155.39999, "duration": 1.0, "label": "UNK", "uniq_id": null}
{"audio_filepath": "../Dataset/Audio/Dev\\zyffh.wav", "offset": 155.89999, "duration": 1.0, "label": "UNK", "uniq_id": null}
{"audio_filepath": "../Dataset/Audio/Dev\\zyffh.wav", "offset": 156.39999, "duration": 1.0, "label": "UNK", "uniq_id": null}
{"audio_filepath": "../Dataset/Audio/Dev\\zyffh.wav", "offset": 156.89999, "duration": 1.0, "label": "UNK", "uniq_id": null}
{"audio_filepath": "../Dataset/Audio/Dev\\zyffh.wav", "offset": 157.39999, "duration": 1.0, "label": "UNK", "uniq_id": null}
{"audio_filepath": "../Dataset/Audio/Dev\\zyffh.wav", "offset": 157.89999, "duration": 1.0, "label": "UNK", "uniq_id": null}
{"audio_filepath": "../Dataset/Audio/Dev\\zyffh.wav", "offset": 158.39999, "duration": 1.0, "label": "UNK", "uniq_id": null}
{"audio_filepath": "../Dataset/Audio/Dev\\zyffh.wav", "offset": 158.89999, "duration": 1.0, "label": "UNK", "uniq_id": null}
{"audio_filepath": "../Dataset/Audio/Dev\\zyffh.wav", "offset": 159.39999, "duration": 1.0, "label": "UNK", "uniq_id": null}
{"audio_filepath": "../Dataset/Audio/Dev\\zyffh.wav", "offset": 159.89999, "duration": 1.0, "label": "UNK", "uniq_id": null}
{"audio_filepath": "../Dataset/Audio/Dev\\zyffh.wav", "offset": 160.39999, "duration": 1.0, "label": "UNK", "uniq_id": null}
{"audio_filepath": "../Dataset/Audio/Dev\\zyffh.wav", "offset": 160.89999, "duration": 1.0, "label": "UNK", "uniq_id": null}
{"audio_filepath": "../Dataset/Audio/Dev\\zyffh.wav", "offset": 161.39999, "duration": 1.0, "label": "UNK", "uniq_id": null}
{"audio_filepath": "../Dataset/Audio/Dev\\zyffh.wav", "offset": 161.89999, "duration": 1.0, "label": "UNK", "uniq_id": null}
{"audio_filepath": "../Dataset/Audio/Dev\\zyffh.wav", "offset": 162.39999, "duration": 1.0, "label": "UNK", "uniq_id": null}
{"audio_filepath": "../Dataset/Audio/Dev\\zyffh.wav", "offset": 162.89999, "duration": 1.0, "label": "UNK", "uniq_id": null}
{"audio_filepath": "../Dataset/Audio/Dev\\zyffh.wav", "offset": 163.39999, "duration": 1.0, "label": "UNK", "uniq_id": null}
{"audio_filepath": "../Dataset/Audio/Dev\\zyffh.wav", "offset": 163.89999, "duration": 1.0, "label": "UNK", "uniq_id": null}
{"audio_filepath": "../Dataset/Audio/Dev\\zyffh.wav", "offset": 164.39999, "duration": 0.7600099999999941, "label": "UNK", "uniq_id": null}
{"audio_filepath": "../Dataset/Audio/Dev\\zyffh.wav", "offset": 165.39999, "duration": 1.0, "label": "UNK", "uniq_id": null}
{"audio_filepath": "../Dataset/Audio/Dev\\zyffh.wav", "offset": 165.89999, "duration": 1.0, "label": "UNK", "uniq_id": null}
{"audio_filepath": "../Dataset/Audio/Dev\\zyffh.wav", "offset": 166.39999, "duration": 1.0, "label": "UNK", "uniq_id": null}
{"audio_filepath": "../Dataset/Audio/Dev\\zyffh.wav", "offset": 166.89999, "duration": 1.0, "label": "UNK", "uniq_id": null}
{"audio_filepath": "../Dataset/Audio/Dev\\zyffh.wav", "offset": 167.39999, "duration": 1.0, "label": "UNK", "uniq_id": null}
{"audio_filepath": "../Dataset/Audio/Dev\\zyffh.wav", "offset": 167.89999, "duration": 1.0, "label": "UNK", "uniq_id": null}
{"audio_filepath": "../Dataset/Audio/Dev\\zyffh.wav", "offset": 168.39999, "duration": 1.0, "label": "UNK", "uniq_id": null}
{"audio_filepath": "../Dataset/Audio/Dev\\zyffh.wav", "offset": 168.89999, "duration": 1.0, "label": "UNK", "uniq_id": null}
{"audio_filepath": "../Dataset/Audio/Dev\\zyffh.wav", "offset": 169.39999, "duration": 1.0, "label": "UNK", "uniq_id": null}
{"audio_filepath": "../Dataset/Audio/Dev\\zyffh.wav", "offset": 169.89999, "duration": 1.0, "label": "UNK", "uniq_id": null}
{"audio_filepath": "../Dataset/Audio/Dev\\zyffh.wav", "offset": 170.39999, "duration": 1.0, "label": "UNK", "uniq_id": null}
{"audio_filepath": "../Dataset/Audio/Dev\\zyffh.wav", "offset": 170.89999, "duration": 1.0, "label": "UNK", "uniq_id": null}
{"audio_filepath": "../Dataset/Audio/Dev\\zyffh.wav", "offset": 171.39999, "duration": 1.0, "label": "UNK", "uniq_id": null}
{"audio_filepath": "../Dataset/Audio/Dev\\zyffh.wav", "offset": 171.89999, "duration": 1.0, "label": "UNK", "uniq_id": null}
{"audio_filepath": "../Dataset/Audio/Dev\\zyffh.wav", "offset": 172.39999, "duration": 1.0, "label": "UNK", "uniq_id": null}
{"audio_filepath": "../Dataset/Audio/Dev\\zyffh.wav", "offset": 172.89999, "duration": 1.0, "label": "UNK", "uniq_id": null}
{"audio_filepath": "../Dataset/Audio/Dev\\zyffh.wav", "offset": 173.39999, "duration": 1.0, "label": "UNK", "uniq_id": null}
{"audio_filepath": "../Dataset/Audio/Dev\\zyffh.wav", "offset": 173.89999, "duration": 1.0, "label": "UNK", "uniq_id": null}
{"audio_filepath": "../Dataset/Audio/Dev\\zyffh.wav", "offset": 174.39999, "duration": 1.0, "label": "UNK", "uniq_id": null}
{"audio_filepath": "../Dataset/Audio/Dev\\zyffh.wav", "offset": 174.89999, "duration": 1.0, "label": "UNK", "uniq_id": null}
{"audio_filepath": "../Dataset/Audio/Dev\\zyffh.wav", "offset": 175.39999, "duration": 1.0, "label": "UNK", "uniq_id": null}
{"audio_filepath": "../Dataset/Audio/Dev\\zyffh.wav", "offset": 175.89999, "duration": 1.0, "label": "UNK", "uniq_id": null}
{"audio_filepath": "../Dataset/Audio/Dev\\zyffh.wav", "offset": 176.39999, "duration": 1.0, "label": "UNK", "uniq_id": null}
{"audio_filepath": "../Dataset/Audio/Dev\\zyffh.wav", "offset": 176.89999, "duration": 1.0, "label": "UNK", "uniq_id": null}
{"audio_filepath": "../Dataset/Audio/Dev\\zyffh.wav", "offset": 177.39999, "duration": 1.0, "label": "UNK", "uniq_id": null}
{"audio_filepath": "../Dataset/Audio/Dev\\zyffh.wav", "offset": 177.89999, "duration": 1.0, "label": "UNK", "uniq_id": null}
{"audio_filepath": "../Dataset/Audio/Dev\\zyffh.wav", "offset": 178.39999, "duration": 1.0, "label": "UNK", "uniq_id": null}
{"audio_filepath": "../Dataset/Audio/Dev\\zyffh.wav", "offset": 178.89999, "duration": 1.0, "label": "UNK", "uniq_id": null}
{"audio_filepath": "../Dataset/Audio/Dev\\zyffh.wav", "offset": 179.39999, "duration": 1.0, "label": "UNK", "uniq_id": null}
{"audio_filepath": "../Dataset/Audio/Dev\\zyffh.wav", "offset": 179.89999, "duration": 1.0, "label": "UNK", "uniq_id": null}
{"audio_filepath": "../Dataset/Audio/Dev\\zyffh.wav", "offset": 180.39999, "duration": 1.0, "label": "UNK", "uniq_id": null}
{"audio_filepath": "../Dataset/Audio/Dev\\zyffh.wav", "offset": 180.89999, "duration": 1.0, "label": "UNK", "uniq_id": null}
{"audio_filepath": "../Dataset/Audio/Dev\\zyffh.wav", "offset": 181.39999, "duration": 1.0, "label": "UNK", "uniq_id": null}
{"audio_filepath": "../Dataset/Audio/Dev\\zyffh.wav", "offset": 181.89999, "duration": 1.0, "label": "UNK", "uniq_id": null}
{"audio_filepath": "../Dataset/Audio/Dev\\zyffh.wav", "offset": 182.39999, "duration": 1.0, "label": "UNK", "uniq_id": null}
{"audio_filepath": "../Dataset/Audio/Dev\\zyffh.wav", "offset": 182.89999, "duration": 1.0, "label": "UNK", "uniq_id": null}
{"audio_filepath": "../Dataset/Audio/Dev\\zyffh.wav", "offset": 183.39999, "duration": 1.0, "label": "UNK", "uniq_id": null}
{"audio_filepath": "../Dataset/Audio/Dev\\zyffh.wav", "offset": 183.89999, "duration": 1.0, "label": "UNK", "uniq_id": null}
{"audio_filepath": "../Dataset/Audio/Dev\\zyffh.wav", "offset": 184.39999, "duration": 1.0, "label": "UNK", "uniq_id": null}
{"audio_filepath": "../Dataset/Audio/Dev\\zyffh.wav", "offset": 184.89999, "duration": 1.0, "label": "UNK", "uniq_id": null}
{"audio_filepath": "../Dataset/Audio/Dev\\zyffh.wav", "offset": 185.39999, "duration": 1.0, "label": "UNK", "uniq_id": null}
{"audio_filepath": "../Dataset/Audio/Dev\\zyffh.wav", "offset": 185.89999, "duration": 1.0, "label": "UNK", "uniq_id": null}
{"audio_filepath": "../Dataset/Audio/Dev\\zyffh.wav", "offset": 186.39999, "duration": 1.0, "label": "UNK", "uniq_id": null}
{"audio_filepath": "../Dataset/Audio/Dev\\zyffh.wav", "offset": 186.89999, "duration": 1.0, "label": "UNK", "uniq_id": null}
{"audio_filepath": "../Dataset/Audio/Dev\\zyffh.wav", "offset": 187.39999, "duration": 1.0, "label": "UNK", "uniq_id": null}
{"audio_filepath": "../Dataset/Audio/Dev\\zyffh.wav", "offset": 187.89999, "duration": 1.0, "label": "UNK", "uniq_id": null}
{"audio_filepath": "../Dataset/Audio/Dev\\zyffh.wav", "offset": 188.39999, "duration": 1.0, "label": "UNK", "uniq_id": null}
{"audio_filepath": "../Dataset/Audio/Dev\\zyffh.wav", "offset": 188.89999, "duration": 1.0, "label": "UNK", "uniq_id": null}
{"audio_filepath": "../Dataset/Audio/Dev\\zyffh.wav", "offset": 189.39999, "duration": 1.0, "label": "UNK", "uniq_id": null}
{"audio_filepath": "../Dataset/Audio/Dev\\zyffh.wav", "offset": 189.89999, "duration": 1.0, "label": "UNK", "uniq_id": null}
{"audio_filepath": "../Dataset/Audio/Dev\\zyffh.wav", "offset": 190.39999, "duration": 1.0, "label": "UNK", "uniq_id": null}
{"audio_filepath": "../Dataset/Audio/Dev\\zyffh.wav", "offset": 190.89999, "duration": 1.0, "label": "UNK", "uniq_id": null}
{"audio_filepath": "../Dataset/Audio/Dev\\zyffh.wav", "offset": 191.39999, "duration": 1.0, "label": "UNK", "uniq_id": null}
{"audio_filepath": "../Dataset/Audio/Dev\\zyffh.wav", "offset": 191.89999, "duration": 1.0, "label": "UNK", "uniq_id": null}
{"audio_filepath": "../Dataset/Audio/Dev\\zyffh.wav", "offset": 192.39999, "duration": 0.7199999999999989, "label": "UNK", "uniq_id": null}
{"audio_filepath": "../Dataset/Audio/Dev\\zyffh.wav", "offset": 193.8, "duration": 1.0, "label": "UNK", "uniq_id": null}
{"audio_filepath": "../Dataset/Audio/Dev\\zyffh.wav", "offset": 194.3, "duration": 1.0, "label": "UNK", "uniq_id": null}
{"audio_filepath": "../Dataset/Audio/Dev\\zyffh.wav", "offset": 194.8, "duration": 1.0, "label": "UNK", "uniq_id": null}
{"audio_filepath": "../Dataset/Audio/Dev\\zyffh.wav", "offset": 195.3, "duration": 1.0, "label": "UNK", "uniq_id": null}
{"audio_filepath": "../Dataset/Audio/Dev\\zyffh.wav", "offset": 195.8, "duration": 1.0, "label": "UNK", "uniq_id": null}
{"audio_filepath": "../Dataset/Audio/Dev\\zyffh.wav", "offset": 196.3, "duration": 1.0, "label": "UNK", "uniq_id": null}
{"audio_filepath": "../Dataset/Audio/Dev\\zyffh.wav", "offset": 196.8, "duration": 1.0, "label": "UNK", "uniq_id": null}
{"audio_filepath": "../Dataset/Audio/Dev\\zyffh.wav", "offset": 197.3, "duration": 1.0, "label": "UNK", "uniq_id": null}
{"audio_filepath": "../Dataset/Audio/Dev\\zyffh.wav", "offset": 197.8, "duration": 1.0, "label": "UNK", "uniq_id": null}
{"audio_filepath": "../Dataset/Audio/Dev\\zyffh.wav", "offset": 198.3, "duration": 1.0, "label": "UNK", "uniq_id": null}
{"audio_filepath": "../Dataset/Audio/Dev\\zyffh.wav", "offset": 198.8, "duration": 1.0, "label": "UNK", "uniq_id": null}
{"audio_filepath": "../Dataset/Audio/Dev\\zyffh.wav", "offset": 199.3, "duration": 1.0, "label": "UNK", "uniq_id": null}
{"audio_filepath": "../Dataset/Audio/Dev\\zyffh.wav", "offset": 199.8, "duration": 1.0, "label": "UNK", "uniq_id": null}
{"audio_filepath": "../Dataset/Audio/Dev\\zyffh.wav", "offset": 200.3, "duration": 1.0, "label": "UNK", "uniq_id": null}
{"audio_filepath": "../Dataset/Audio/Dev\\zyffh.wav", "offset": 200.8, "duration": 0.7599899999999877, "label": "UNK", "uniq_id": null}
{"audio_filepath": "../Dataset/Audio/Dev\\zyffh.wav", "offset": 202.16, "duration": 1.0, "label": "UNK", "uniq_id": null}
{"audio_filepath": "../Dataset/Audio/Dev\\zyffh.wav", "offset": 202.66, "duration": 1.0, "label": "UNK", "uniq_id": null}
{"audio_filepath": "../Dataset/Audio/Dev\\zyffh.wav", "offset": 203.16, "duration": 1.0, "label": "UNK", "uniq_id": null}
{"audio_filepath": "../Dataset/Audio/Dev\\zyffh.wav", "offset": 203.66, "duration": 1.0, "label": "UNK", "uniq_id": null}
{"audio_filepath": "../Dataset/Audio/Dev\\zyffh.wav", "offset": 204.16, "duration": 1.0, "label": "UNK", "uniq_id": null}
{"audio_filepath": "../Dataset/Audio/Dev\\zyffh.wav", "offset": 204.66, "duration": 1.0, "label": "UNK", "uniq_id": null}
{"audio_filepath": "../Dataset/Audio/Dev\\zyffh.wav", "offset": 205.16, "duration": 1.0, "label": "UNK", "uniq_id": null}
{"audio_filepath": "../Dataset/Audio/Dev\\zyffh.wav", "offset": 205.66, "duration": 1.0, "label": "UNK", "uniq_id": null}
{"audio_filepath": "../Dataset/Audio/Dev\\zyffh.wav", "offset": 206.16, "duration": 1.0, "label": "UNK", "uniq_id": null}
{"audio_filepath": "../Dataset/Audio/Dev\\zyffh.wav", "offset": 206.66, "duration": 1.0, "label": "UNK", "uniq_id": null}
{"audio_filepath": "../Dataset/Audio/Dev\\zyffh.wav", "offset": 207.16, "duration": 1.0, "label": "UNK", "uniq_id": null}
{"audio_filepath": "../Dataset/Audio/Dev\\zyffh.wav", "offset": 207.66, "duration": 1.0, "label": "UNK", "uniq_id": null}
{"audio_filepath": "../Dataset/Audio/Dev\\zyffh.wav", "offset": 208.16, "duration": 1.0, "label": "UNK", "uniq_id": null}
{"audio_filepath": "../Dataset/Audio/Dev\\zyffh.wav", "offset": 208.66, "duration": 1.0, "label": "UNK", "uniq_id": null}
{"audio_filepath": "../Dataset/Audio/Dev\\zyffh.wav", "offset": 209.16, "duration": 1.0, "label": "UNK", "uniq_id": null}
{"audio_filepath": "../Dataset/Audio/Dev\\zyffh.wav", "offset": 209.66, "duration": 1.0, "label": "UNK", "uniq_id": null}
{"audio_filepath": "../Dataset/Audio/Dev\\zyffh.wav", "offset": 210.16, "duration": 1.0, "label": "UNK", "uniq_id": null}
{"audio_filepath": "../Dataset/Audio/Dev\\zyffh.wav", "offset": 210.66, "duration": 1.0, "label": "UNK", "uniq_id": null}
{"audio_filepath": "../Dataset/Audio/Dev\\zyffh.wav", "offset": 211.16, "duration": 1.0, "label": "UNK", "uniq_id": null}
{"audio_filepath": "../Dataset/Audio/Dev\\zyffh.wav", "offset": 211.66, "duration": 1.0, "label": "UNK", "uniq_id": null}
{"audio_filepath": "../Dataset/Audio/Dev\\zyffh.wav", "offset": 212.16, "duration": 1.0, "label": "UNK", "uniq_id": null}
{"audio_filepath": "../Dataset/Audio/Dev\\zyffh.wav", "offset": 212.66, "duration": 1.0, "label": "UNK", "uniq_id": null}
{"audio_filepath": "../Dataset/Audio/Dev\\zyffh.wav", "offset": 213.16, "duration": 1.0, "label": "UNK", "uniq_id": null}
{"audio_filepath": "../Dataset/Audio/Dev\\zyffh.wav", "offset": 213.66, "duration": 1.0, "label": "UNK", "uniq_id": null}
{"audio_filepath": "../Dataset/Audio/Dev\\zyffh.wav", "offset": 214.16, "duration": 1.0, "label": "UNK", "uniq_id": null}
{"audio_filepath": "../Dataset/Audio/Dev\\zyffh.wav", "offset": 214.66, "duration": 1.0, "label": "UNK", "uniq_id": null}
{"audio_filepath": "../Dataset/Audio/Dev\\zyffh.wav", "offset": 215.16, "duration": 1.0, "label": "UNK", "uniq_id": null}
{"audio_filepath": "../Dataset/Audio/Dev\\zyffh.wav", "offset": 215.66, "duration": 1.0, "label": "UNK", "uniq_id": null}
{"audio_filepath": "../Dataset/Audio/Dev\\zyffh.wav", "offset": 216.16, "duration": 1.0, "label": "UNK", "uniq_id": null}
{"audio_filepath": "../Dataset/Audio/Dev\\zyffh.wav", "offset": 216.66, "duration": 1.0, "label": "UNK", "uniq_id": null}
{"audio_filepath": "../Dataset/Audio/Dev\\zyffh.wav", "offset": 217.16, "duration": 1.0, "label": "UNK", "uniq_id": null}
{"audio_filepath": "../Dataset/Audio/Dev\\zyffh.wav", "offset": 217.66, "duration": 1.0, "label": "UNK", "uniq_id": null}
{"audio_filepath": "../Dataset/Audio/Dev\\zyffh.wav", "offset": 218.16, "duration": 1.0, "label": "UNK", "uniq_id": null}
{"audio_filepath": "../Dataset/Audio/Dev\\zyffh.wav", "offset": 218.66, "duration": 1.0, "label": "UNK", "uniq_id": null}
{"audio_filepath": "../Dataset/Audio/Dev\\zyffh.wav", "offset": 219.16, "duration": 1.0, "label": "UNK", "uniq_id": null}
{"audio_filepath": "../Dataset/Audio/Dev\\zyffh.wav", "offset": 219.66, "duration": 1.0, "label": "UNK", "uniq_id": null}
{"audio_filepath": "../Dataset/Audio/Dev\\zyffh.wav", "offset": 220.16, "duration": 1.0, "label": "UNK", "uniq_id": null}
{"audio_filepath": "../Dataset/Audio/Dev\\zyffh.wav", "offset": 220.66, "duration": 1.0, "label": "UNK", "uniq_id": null}
{"audio_filepath": "../Dataset/Audio/Dev\\zyffh.wav", "offset": 221.16, "duration": 1.0, "label": "UNK", "uniq_id": null}
{"audio_filepath": "../Dataset/Audio/Dev\\zyffh.wav", "offset": 221.66, "duration": 1.0, "label": "UNK", "uniq_id": null}
{"audio_filepath": "../Dataset/Audio/Dev\\zyffh.wav", "offset": 222.16, "duration": 1.0, "label": "UNK", "uniq_id": null}
{"audio_filepath": "../Dataset/Audio/Dev\\zyffh.wav", "offset": 222.66, "duration": 1.0, "label": "UNK", "uniq_id": null}
{"audio_filepath": "../Dataset/Audio/Dev\\zyffh.wav", "offset": 223.16, "duration": 1.0, "label": "UNK", "uniq_id": null}
{"audio_filepath": "../Dataset/Audio/Dev\\zyffh.wav", "offset": 223.66, "duration": 1.0, "label": "UNK", "uniq_id": null}
{"audio_filepath": "../Dataset/Audio/Dev\\zyffh.wav", "offset": 224.16, "duration": 1.0, "label": "UNK", "uniq_id": null}
{"audio_filepath": "../Dataset/Audio/Dev\\zyffh.wav", "offset": 224.66, "duration": 1.0, "label": "UNK", "uniq_id": null}
{"audio_filepath": "../Dataset/Audio/Dev\\zyffh.wav", "offset": 225.16, "duration": 1.0, "label": "UNK", "uniq_id": null}
{"audio_filepath": "../Dataset/Audio/Dev\\zyffh.wav", "offset": 225.66, "duration": 1.0, "label": "UNK", "uniq_id": null}
{"audio_filepath": "../Dataset/Audio/Dev\\zyffh.wav", "offset": 226.16, "duration": 1.0, "label": "UNK", "uniq_id": null}
{"audio_filepath": "../Dataset/Audio/Dev\\zyffh.wav", "offset": 226.66, "duration": 1.0, "label": "UNK", "uniq_id": null}
{"audio_filepath": "../Dataset/Audio/Dev\\zyffh.wav", "offset": 227.16, "duration": 1.0, "label": "UNK", "uniq_id": null}
{"audio_filepath": "../Dataset/Audio/Dev\\zyffh.wav", "offset": 227.66, "duration": 1.0, "label": "UNK", "uniq_id": null}
{"audio_filepath": "../Dataset/Audio/Dev\\zyffh.wav", "offset": 228.16, "duration": 1.0, "label": "UNK", "uniq_id": null}
{"audio_filepath": "../Dataset/Audio/Dev\\zyffh.wav", "offset": 228.66, "duration": 1.0, "label": "UNK", "uniq_id": null}
{"audio_filepath": "../Dataset/Audio/Dev\\zyffh.wav", "offset": 229.16, "duration": 1.0, "label": "UNK", "uniq_id": null}
{"audio_filepath": "../Dataset/Audio/Dev\\zyffh.wav", "offset": 229.66, "duration": 1.0, "label": "UNK", "uniq_id": null}
{"audio_filepath": "../Dataset/Audio/Dev\\zyffh.wav", "offset": 230.16, "duration": 1.0, "label": "UNK", "uniq_id": null}
{"audio_filepath": "../Dataset/Audio/Dev\\zyffh.wav", "offset": 230.66, "duration": 1.0, "label": "UNK", "uniq_id": null}
{"audio_filepath": "../Dataset/Audio/Dev\\zyffh.wav", "offset": 231.16, "duration": 1.0, "label": "UNK", "uniq_id": null}
{"audio_filepath": "../Dataset/Audio/Dev\\zyffh.wav", "offset": 231.66, "duration": 1.0, "label": "UNK", "uniq_id": null}
{"audio_filepath": "../Dataset/Audio/Dev\\zyffh.wav", "offset": 232.16, "duration": 1.0, "label": "UNK", "uniq_id": null}
{"audio_filepath": "../Dataset/Audio/Dev\\zyffh.wav", "offset": 232.66, "duration": 1.0, "label": "UNK", "uniq_id": null}
{"audio_filepath": "../Dataset/Audio/Dev\\zyffh.wav", "offset": 233.16, "duration": 1.0, "label": "UNK", "uniq_id": null}
{"audio_filepath": "../Dataset/Audio/Dev\\zyffh.wav", "offset": 233.66, "duration": 1.0, "label": "UNK", "uniq_id": null}
{"audio_filepath": "../Dataset/Audio/Dev\\zyffh.wav", "offset": 234.16, "duration": 1.0, "label": "UNK", "uniq_id": null}
{"audio_filepath": "../Dataset/Audio/Dev\\zyffh.wav", "offset": 234.66, "duration": 1.0, "label": "UNK", "uniq_id": null}
{"audio_filepath": "../Dataset/Audio/Dev\\zyffh.wav", "offset": 235.16, "duration": 1.0, "label": "UNK", "uniq_id": null}
{"audio_filepath": "../Dataset/Audio/Dev\\zyffh.wav", "offset": 235.66, "duration": 1.0, "label": "UNK", "uniq_id": null}
{"audio_filepath": "../Dataset/Audio/Dev\\zyffh.wav", "offset": 236.16, "duration": 1.0, "label": "UNK", "uniq_id": null}
{"audio_filepath": "../Dataset/Audio/Dev\\zyffh.wav", "offset": 236.66, "duration": 0.9799999999999898, "label": "UNK", "uniq_id": null}
{"audio_filepath": "../Dataset/Audio/Dev\\zyffh.wav", "offset": 238.2, "duration": 1.0, "label": "UNK", "uniq_id": null}
{"audio_filepath": "../Dataset/Audio/Dev\\zyffh.wav", "offset": 238.7, "duration": 1.0, "label": "UNK", "uniq_id": null}
{"audio_filepath": "../Dataset/Audio/Dev\\zyffh.wav", "offset": 239.2, "duration": 1.0, "label": "UNK", "uniq_id": null}
{"audio_filepath": "../Dataset/Audio/Dev\\zyffh.wav", "offset": 239.7, "duration": 1.0, "label": "UNK", "uniq_id": null}
{"audio_filepath": "../Dataset/Audio/Dev\\zyffh.wav", "offset": 240.2, "duration": 1.0, "label": "UNK", "uniq_id": null}
{"audio_filepath": "../Dataset/Audio/Dev\\zyffh.wav", "offset": 240.7, "duration": 1.0, "label": "UNK", "uniq_id": null}
{"audio_filepath": "../Dataset/Audio/Dev\\zyffh.wav", "offset": 241.2, "duration": 1.0, "label": "UNK", "uniq_id": null}
{"audio_filepath": "../Dataset/Audio/Dev\\zyffh.wav", "offset": 241.7, "duration": 0.7400100000000123, "label": "UNK", "uniq_id": null}
{"audio_filepath": "../Dataset/Audio/Dev\\zyffh.wav", "offset": 242.92, "duration": 1.0, "label": "UNK", "uniq_id": null}
{"audio_filepath": "../Dataset/Audio/Dev\\zyffh.wav", "offset": 243.42, "duration": 1.0, "label": "UNK", "uniq_id": null}
{"audio_filepath": "../Dataset/Audio/Dev\\zyffh.wav", "offset": 243.92, "duration": 1.0, "label": "UNK", "uniq_id": null}
{"audio_filepath": "../Dataset/Audio/Dev\\zyffh.wav", "offset": 244.42, "duration": 1.0, "label": "UNK", "uniq_id": null}
{"audio_filepath": "../Dataset/Audio/Dev\\zyffh.wav", "offset": 244.92, "duration": 1.0, "label": "UNK", "uniq_id": null}
{"audio_filepath": "../Dataset/Audio/Dev\\zyffh.wav", "offset": 245.42, "duration": 0.7800000000000011, "label": "UNK", "uniq_id": null}
{"audio_filepath": "../Dataset/Audio/Dev\\zyffh.wav", "offset": 246.88, "duration": 1.0, "label": "UNK", "uniq_id": null}
{"audio_filepath": "../Dataset/Audio/Dev\\zyffh.wav", "offset": 247.38, "duration": 0.6200000000000045, "label": "UNK", "uniq_id": null}
{"audio_filepath": "../Dataset/Audio/Dev\\zyffh.wav", "offset": 248.12, "duration": 1.0, "label": "UNK", "uniq_id": null}
{"audio_filepath": "../Dataset/Audio/Dev\\zyffh.wav", "offset": 248.62, "duration": 1.0, "label": "UNK", "uniq_id": null}
{"audio_filepath": "../Dataset/Audio/Dev\\zyffh.wav", "offset": 249.12, "duration": 1.0, "label": "UNK", "uniq_id": null}
{"audio_filepath": "../Dataset/Audio/Dev\\zyffh.wav", "offset": 249.62, "duration": 1.0, "label": "UNK", "uniq_id": null}
{"audio_filepath": "../Dataset/Audio/Dev\\zyffh.wav", "offset": 250.12, "duration": 1.0, "label": "UNK", "uniq_id": null}
{"audio_filepath": "../Dataset/Audio/Dev\\zyffh.wav", "offset": 250.62, "duration": 1.0, "label": "UNK", "uniq_id": null}
{"audio_filepath": "../Dataset/Audio/Dev\\zyffh.wav", "offset": 251.12, "duration": 0.9199999999999875, "label": "UNK", "uniq_id": null}
